{
  "events": [
    {
      "id": "1",
      "title": "Tech Founders Mixer",
      "type": "formal",
      "date": "2025-12-15",
      "time": "18:00",
      "venue": "WeWork Galaxy",
      "hostId": "h1",
      "price": 0,
      "description": "Networking event for early-stage tech founders.",
      "image": "https://images.unsplash.com/photo-1515187029135-18ee286d815b?auto=format&fit=crop&q=80",
      "tags": [
        "networking",
        "tech",
        "startup"
      ],
      "isSuperhost": true
    },
    {
      "id": "2",
      "title": "Underground Jazz Night",
      "type": "informal",
      "date": "2025-12-16",
      "time": "21:00",
      "venue": "The Blue Note",
      "hostId": "h2",
      "price": 20,
      "description": "Intimate jazz session with local legends.",
      "image": "https://images.unsplash.com/photo-1514525253440-b393452e8d26?auto=format&fit=crop&q=80",
      "tags": [
        "music",
        "jazz",
        "live"
      ],
      "isSuperhost": false
    },
    {
      "id": "3",
      "title": "React Advanced Workshop",
      "type": "formal",
      "date": "2025-12-20",
      "time": "10:00",
      "venue": "TechHub",
      "hostId": "h1",
      "price": 150,
      "description": "Deep dive into React Server Components and performance.",
      "image": "https://images.unsplash.com/photo-1531482615713-2afd69097998?auto=format&fit=crop&q=80",
      "tags": [
        "coding",
        "react",
        "workshop"
      ],
      "isSuperhost": true
    },
    {
      "id": "4",
      "title": "Rooftop House Party",
      "type": "informal",
      "date": "2025-12-18",
      "time": "22:00",
      "venue": "Skyline Lofts",
      "hostId": "h3",
      "price": 15,
      "description": "Good vibes, great view, and even better music.",
      "image": "https://images.unsplash.com/photo-1516450360452-9312f5e86fc7?auto=format&fit=crop&q=80",
      "tags": [
        "party",
        "rooftop",
        "social"
      ],
      "isSuperhost": false
    },
    {
      "id": "5",
      "title": "Product Design Sprint",
      "type": "formal",
      "date": "2025-12-22",
      "time": "09:00",
      "venue": "Design Studio X",
      "hostId": "h4",
      "price": 200,
      "description": "Learn how to run a design sprint from scratch.",
      "image": "https://images.unsplash.com/photo-1552664730-d307ca884978?auto=format&fit=crop&q=80",
      "tags": [
        "design",
        "product",
        "workshop"
      ],
      "isSuperhost": true
    },
    {
      "id": "6",
      "title": "Indie Game Jam",
      "type": "informal",
      "date": "2025-12-25",
      "time": "14:00",
      "venue": "Pixel Bar",
      "hostId": "h5",
      "price": 10,
      "description": "Showcase your indie games and playtest others.",
      "image": "https://images.unsplash.com/photo-1552820728-8b83bb6b773f?auto=format&fit=crop&q=80",
      "tags": [
        "gaming",
        "indie",
        "social"
      ],
      "isSuperhost": false
    },
    {
      "id": "7",
      "title": "AI Ethics Panel",
      "type": "formal",
      "date": "2025-12-28",
      "time": "19:00",
      "venue": "University Hall",
      "hostId": "h1",
      "price": 0,
      "description": "Discussion on the future of AI and ethics.",
      "image": "https://images.unsplash.com/photo-1526628953301-3e589a6a8b74?auto=format&fit=crop&q=80",
      "tags": [
        "ai",
        "ethics",
        "panel"
      ],
      "isSuperhost": true
    },
    {
      "id": "8",
      "title": "Techno Bunker Rave",
      "type": "informal",
      "date": "2025-12-31",
      "time": "23:00",
      "venue": "Secret Location",
      "hostId": "h2",
      "price": 30,
      "description": "NYE Techno rave. Location revealed 2 hours before.",
      "image": "https://images.unsplash.com/photo-1574391884720-2bbc37e3ae8f?auto=format&fit=crop&q=80",
      "tags": [
        "music",
        "techno",
        "rave"
      ],
      "isSuperhost": false
    },
    {
      "id": "9",
      "title": "Marketing Strategy Masterclass",
      "type": "formal",
      "date": "2026-01-05",
      "time": "11:00",
      "venue": "Business Center",
      "hostId": "h4",
      "price": 100,
      "description": "Master the art of digital marketing strategies.",
      "image": "https://images.unsplash.com/photo-1557804506-669a67965ba0?auto=format&fit=crop&q=80",
      "tags": [
        "marketing",
        "business",
        "masterclass"
      ],
      "isSuperhost": true
    },
    {
      "id": "10",
      "title": "Salsa Social Night",
      "type": "informal",
      "date": "2026-01-07",
      "time": "20:00",
      "venue": "Havana Club",
      "hostId": "h3",
      "price": 15,
      "description": "Learn salsa basics and dance the night away.",
      "image": "https://images.unsplash.com/photo-1546215364-12f3fff5d578?auto=format&fit=crop&q=80",
      "tags": [
        "dance",
        "salsa",
        "social"
      ],
      "isSuperhost": false
    },
    {
      "id": "11",
      "title": "Blockchain Summit 2026",
      "type": "formal",
      "date": "2026-01-10",
      "time": "09:00",
      "venue": "Convention Center",
      "hostId": "h1",
      "price": 300,
      "description": "The biggest blockchain event of the year.",
      "image": "https://images.unsplash.com/photo-1516245834210-c4c14278733f?auto=format&fit=crop&q=80",
      "tags": [
        "blockchain",
        "crypto",
        "conference"
      ],
      "isSuperhost": true
    },
    {
      "id": "12",
      "title": "Comedy Open Mic",
      "type": "informal",
      "date": "2026-01-12",
      "time": "20:30",
      "venue": "The Laugh Factory",
      "hostId": "h5",
      "price": 5,
      "description": "Local comedians testing out new material.",
      "image": "https://images.unsplash.com/photo-1585699324551-f6c309eedeca?auto=format&fit=crop&q=80",
      "tags": [
        "comedy",
        "openmic",
        "fun"
      ],
      "isSuperhost": false
    },
    {
      "id": "13",
      "title": "Sustainable Living Workshop",
      "type": "formal",
      "date": "2026-01-15",
      "time": "14:00",
      "venue": "Green Hub",
      "hostId": "h4",
      "price": 50,
      "description": "Practical tips for a more sustainable lifestyle.",
      "image": "https://images.unsplash.com/photo-1542601906990-b4d3fb778b09?auto=format&fit=crop&q=80",
      "tags": [
        "sustainability",
        "workshop",
        "green"
      ],
      "isSuperhost": true
    },
    {
      "id": "14",
      "title": "Board Game Marathon",
      "type": "informal",
      "date": "2026-01-18",
      "time": "12:00",
      "venue": "Dice & Drinks",
      "hostId": "h3",
      "price": 5,
      "description": "All day board gaming event. Bring your own or play ours.",
      "image": "https://images.unsplash.com/photo-1610890716171-6b1c9f2bdabf?auto=format&fit=crop&q=80",
      "tags": [
        "boardgames",
        "gaming",
        "social"
      ],
      "isSuperhost": false
    },
    {
      "id": "15",
      "title": "Investment Banking 101",
      "type": "formal",
      "date": "2026-01-20",
      "time": "18:00",
      "venue": "Finance Tower",
      "hostId": "h1",
      "price": 0,
      "description": "Introduction to careers in investment banking.",
      "image": "https://images.unsplash.com/photo-1556761175-5973dc0f32e7?auto=format&fit=crop&q=80",
      "tags": [
        "finance",
        "banking",
        "career"
      ],
      "isSuperhost": true
    },
    {
      "id": "5a0f",
      "title": "House Party",
      "type": "informal",
      "date": "2025-12-25",
      "time": "18:00",
      "venue": "Purvanchal Royal City Greater Noida",
      "price": "0",
      "description": "BYOB, Good Music, Chill People",
      "image": "",
      "menu": [],
      "hostId": "user-123",
      "tags": [
        "new"
      ],
      "isSuperhost": false
    }
  ],
  "hosts": [
    {
      "id": "h1",
      "name": "Tech Innovators Inc.",
      "verified": true,
      "avatar": "https://api.dicebear.com/7.x/avataaars/svg?seed=Tech"
    },
    {
      "id": "h2",
      "name": "Underground Vibes",
      "verified": false,
      "avatar": "https://api.dicebear.com/7.x/avataaars/svg?seed=Vibes"
    },
    {
      "id": "h3",
      "name": "Social Butterfly",
      "verified": true,
      "avatar": "https://api.dicebear.com/7.x/avataaars/svg?seed=Social"
    },
    {
      "id": "h4",
      "name": "Creative Minds",
      "verified": true,
      "avatar": "https://api.dicebear.com/7.x/avataaars/svg?seed=Creative"
    },
    {
      "id": "h5",
      "name": "Local Heroes",
      "verified": false,
      "avatar": "https://api.dicebear.com/7.x/avataaars/svg?seed=Local"
    }
  ],
  "bookings": [
    {
      "id": "8218",
      "userId": "guest_user",
      "items": [
        {
          "id": "1",
          "title": "Tech Founders Mixer",
          "type": "formal",
          "date": "2025-12-15",
          "time": "18:00",
          "venue": "WeWork Galaxy",
          "hostId": "h1",
          "price": 0,
          "description": "Networking event for early-stage tech founders.",
          "image": "https://images.unsplash.com/photo-1515187029135-18ee286d815b?auto=format&fit=crop&q=80",
          "tags": [
            "networking",
            "tech",
            "startup"
          ],
          "isSuperhost": true,
          "qty": 1
        }
      ],
      "totalAmount": 0,
      "status": "confirmed",
      "paymentId": "txn_fdjphbzde",
      "customer": {
        "name": "Parrv",
        "email": "parrvluthra@gmail.com",
        "phone": "12345678"
      },
      "createdAt": "2025-12-07T11:18:41.262Z"
    },
    {
      "id": "0b43",
      "userId": "guest_user",
      "items": [
        {
          "id": "1",
          "title": "Tech Founders Mixer",
          "type": "formal",
          "date": "2025-12-15",
          "time": "18:00",
          "venue": "WeWork Galaxy",
          "hostId": "h1",
          "price": 0,
          "description": "Networking event for early-stage tech founders.",
          "image": "https://images.unsplash.com/photo-1515187029135-18ee286d815b?auto=format&fit=crop&q=80",
          "tags": [
            "networking",
            "tech",
            "startup"
          ],
          "isSuperhost": true,
          "qty": 1
        },
        {
          "id": "6",
          "title": "Indie Game Jam",
          "type": "informal",
          "date": "2025-12-25",
          "time": "14:00",
          "venue": "Pixel Bar",
          "hostId": "h5",
          "price": 10,
          "description": "Showcase your indie games and playtest others.",
          "image": "https://images.unsplash.com/photo-1552820728-8b83bb6b773f?auto=format&fit=crop&q=80",
          "tags": [
            "gaming",
            "indie",
            "social"
          ],
          "isSuperhost": false,
          "qty": 2
        }
      ],
      "totalAmount": 22,
      "status": "confirmed",
      "paymentId": "txn_soe2tocnr",
      "customer": {
        "name": "parrv",
        "email": "parrvluthra@gmail.com",
        "phone": "9625789901"
      },
      "createdAt": "2025-12-07T11:55:27.960Z"
    },
    {
      "id": "c705",
      "userId": "guest_user",
      "items": [
        {
          "id": "15",
          "title": "Investment Banking 101",
          "type": "formal",
          "date": "2026-01-20",
          "time": "18:00",
          "venue": "Finance Tower",
          "hostId": "h1",
          "price": 0,
          "description": "Introduction to careers in investment banking.",
          "image": "https://images.unsplash.com/photo-1556761175-5973dc0f32e7?auto=format&fit=crop&q=80",
          "tags": [
            "finance",
            "banking",
            "career"
          ],
          "isSuperhost": true,
          "qty": 2
        },
        {
          "id": "5",
          "title": "Product Design Sprint",
          "type": "formal",
          "date": "2025-12-22",
          "time": "09:00",
          "venue": "Design Studio X",
          "hostId": "h4",
          "price": 200,
          "description": "Learn how to run a design sprint from scratch.",
          "image": "https://images.unsplash.com/photo-1552664730-d307ca884978?auto=format&fit=crop&q=80",
          "tags": [
            "design",
            "product",
            "workshop"
          ],
          "isSuperhost": true,
          "qty": 1
        }
      ],
      "totalAmount": 220,
      "status": "confirmed",
      "paymentId": "txn_coxaqikkp",
      "customer": {
        "name": "ggviv",
        "email": "aadit@gmail.com",
        "phone": "12345466789"
      },
      "createdAt": "2025-12-07T12:21:42.853Z"
    }
  ],
  "eventSubmissions": [
    {
      "id": "sub1",
      "hostId": "h1",
      "status": "approved",
      "createdAt": "2025-12-01T10:00:00Z",
      "updatedAt": "2025-12-02T14:00:00Z",
      "title": "Tech Founders Mixer",
      "description": "Networking event for early-stage tech founders.",
      "category": "Networking",
      "type": "formal",
      "date": "2025-12-15",
      "time": "18:00",
      "duration": 120,
      "timezone": "America/Los_Angeles",
      "venue": {
        "name": "WeWork Galaxy",
        "address": "123 Tech Blvd",
        "city": "San Francisco",
        "state": "CA",
        "country": "USA",
        "coordinates": {
          "lat": 37.7749,
          "lng": -122.4194
        }
      },
      "pricing": {
        "isFree": true
      },
      "media": {
        "coverImage": "https://images.unsplash.com/photo-1515187029135-18ee286d815b?auto=format&fit=crop&q=80"
      },
      "tags": [
        "networking",
        "tech",
        "startup"
      ],
      "capacity": 50,
      "requirements": {
        "dresscode": "Smart Casual"
      }
    },
    {
      "id": "sub2",
      "hostId": "h2",
      "status": "pending",
      "createdAt": "2025-12-05T09:00:00Z",
      "updatedAt": "2025-12-05T09:00:00Z",
      "title": "Underground Jazz Night",
      "description": "Intimate jazz session with local legends.",
      "category": "Music",
      "type": "informal",
      "date": "2025-12-16",
      "time": "21:00",
      "duration": 180,
      "timezone": "America/New_York",
      "venue": {
        "name": "The Blue Note",
        "address": "131 W 3rd St",
        "city": "New York",
        "state": "NY",
        "country": "USA"
      },
      "pricing": {
        "isFree": false,
        "ticketTiers": [
          {
            "name": "General Admission",
            "price": 20,
            "quantity": 100
          }
        ]
      },
      "media": {
        "coverImage": "https://images.unsplash.com/photo-1514525253440-b393452e8d26?auto=format&fit=crop&q=80"
      },
      "tags": [
        "music",
        "jazz",
        "live"
      ],
      "capacity": 100,
      "ageRestriction": 21
    },
    {
      "id": "sub3",
      "hostId": "h3",
      "status": "draft",
      "createdAt": "2025-12-06T15:30:00Z",
      "updatedAt": "2025-12-06T16:00:00Z",
      "title": "Rooftop House Party",
      "description": "Good vibes, great view, and even better music.",
      "category": "Party",
      "type": "informal",
      "date": "2025-12-18",
      "time": "22:00",
      "duration": 240,
      "timezone": "America/Los_Angeles",
      "venue": {
        "name": "Skyline Lofts",
        "address": "500 High St",
        "city": "Los Angeles",
        "state": "CA",
        "country": "USA"
      },
      "pricing": {
        "isFree": false,
        "ticketTiers": [
          {
            "name": "Early Bird",
            "price": 10,
            "quantity": 20
          },
          {
            "name": "Standard",
            "price": 15,
            "quantity": 50
          }
        ]
      },
      "media": {
        "coverImage": "https://images.unsplash.com/photo-1516450360452-9312f5e86fc7?auto=format&fit=crop&q=80"
      },
      "tags": [
        "party",
        "rooftop",
        "social"
      ],
      "capacity": 70
    },
    {
      "id": "sub4",
      "hostId": "h4",
      "status": "rejected",
      "createdAt": "2025-12-04T11:00:00Z",
      "updatedAt": "2025-12-04T13:00:00Z",
      "title": "Sketchy Meetup",
      "description": "Meet behind the dumpster.",
      "category": "Other",
      "type": "informal",
      "date": "2025-12-20",
      "time": "02:00",
      "duration": 30,
      "timezone": "America/Chicago",
      "venue": {
        "name": "Alleyway",
        "address": "Unknown",
        "city": "Chicago",
        "state": "IL",
        "country": "USA"
      },
      "pricing": {
        "isFree": true
      },
      "media": {
        "coverImage": "https://example.com/bad-image.jpg"
      },
      "tags": [
        "weird"
      ],
      "capacity": 5,
      "hostNotes": "Rejected due to safety concerns."
    },
    {
      "id": "sub5",
      "hostId": "h1",
      "status": "approved",
      "createdAt": "2025-12-02T09:00:00Z",
      "updatedAt": "2025-12-03T10:00:00Z",
      "title": "React Advanced Workshop",
      "description": "Deep dive into React Server Components and performance.",
      "category": "Education",
      "type": "formal",
      "date": "2025-12-20",
      "time": "10:00",
      "duration": 360,
      "timezone": "America/Los_Angeles",
      "venue": {
        "name": "TechHub",
        "address": "456 Innovation Dr",
        "city": "San Francisco",
        "state": "CA",
        "country": "USA"
      },
      "pricing": {
        "isFree": false,
        "ticketTiers": [
          {
            "name": "Workshop Pass",
            "price": 150,
            "quantity": 30,
            "perks": [
              "Lunch included",
              "Certificate"
            ]
          }
        ]
      },
      "media": {
        "coverImage": "https://images.unsplash.com/photo-1531482615713-2afd69097998?auto=format&fit=crop&q=80"
      },
      "tags": [
        "coding",
        "react",
        "workshop"
      ],
      "capacity": 30,
      "requirements": {
        "prerequisites": [
          "Basic React knowledge",
          "Laptop"
        ]
      }
    }
  ],
  "hostProfiles": [
    {
      "id": "h1",
      "userId": "u1",
      "displayName": "Tech Innovators Inc.",
      "bio": "Leading tech community in SF.",
      "avatar": "https://api.dicebear.com/7.x/avataaars/svg?seed=Tech",
      "verificationStatus": "verified",
      "rating": 4.8,
      "totalEvents": 15,
      "badges": [
        "Superhost",
        "Community Leader"
      ],
      "socialLinks": {
        "website": "https://techinnovators.com",
        "twitter": "https://twitter.com/techinnovators"
      },
      "bankDetails": {
        "accountName": "Tech Innovators Inc.",
        "accountNumber": "****1234",
        "routingNumber": "****5678",
        "bankName": "Silicon Valley Bank"
      }
    },
    {
      "id": "h2",
      "userId": "u2",
      "displayName": "Underground Vibes",
      "bio": "Curating the best underground music scenes.",
      "avatar": "https://api.dicebear.com/7.x/avataaars/svg?seed=Vibes",
      "verificationStatus": "pending",
      "rating": 4.5,
      "totalEvents": 8,
      "badges": [
        "Rising Star"
      ],
      "socialLinks": {
        "instagram": "https://instagram.com/undergroundvibes"
      }
    },
    {
      "id": "h3",
      "userId": "u3",
      "displayName": "Social Butterfly",
      "bio": "Bringing people together one party at a time.",
      "avatar": "https://api.dicebear.com/7.x/avataaars/svg?seed=Social",
      "verificationStatus": "verified",
      "rating": 4.2,
      "totalEvents": 20,
      "badges": [
        "Party Animal"
      ]
    },
    {
      "id": "h4",
      "userId": "u4",
      "displayName": "Creative Minds",
      "bio": "Workshops for creative professionals.",
      "avatar": "https://api.dicebear.com/7.x/avataaars/svg?seed=Creative",
      "verificationStatus": "verified",
      "rating": 4.9,
      "totalEvents": 12,
      "badges": [
        "Superhost",
        "Educator"
      ]
    }
  ],
  "eventAnalytics": [
    {
      "eventId": "1",
      "views": 1250,
      "saves": 340,
      "clicks": 890,
      "bookings": 45,
      "revenue": 0,
      "id": "5e82"
    },
    {
      "eventId": "2",
      "views": 800,
      "saves": 120,
      "clicks": 450,
      "bookings": 85,
      "revenue": 1700,
      "id": "bfbe"
    },
    {
      "eventId": "3",
      "views": 2100,
      "saves": 560,
      "clicks": 1200,
      "bookings": 28,
      "revenue": 4200,
      "id": "514c"
    }
  ]
}